numcodecs_wasm_random_projection/__init__.py
numcodecs_wasm_random_projection/__init__.pyi
numcodecs_wasm_random_projection/codec.wasm
numcodecs_wasm_random_projection/py.typed
numcodecs_wasm_random_projection-0.4.0.dist-info/METADATA
numcodecs_wasm_random_projection-0.4.0.dist-info/WHEEL
numcodecs_wasm_random_projection-0.4.0.dist-info/entry_points.txt
numcodecs_wasm_random_projection-0.4.0.dist-info/top_level.txt
numcodecs_wasm_random_projection-0.4.0.dist-info/RECORD
